request_logging/__init__.py
request_logging/decorators.py
request_logging/utils.py
request_logging/Filters/LoggingFilters.py
request_logging/Filters/__init__.py
request_logging/middleware/RequestResponseLogging.py
request_logging/middleware/__init__.py
request_response_logging-1.0.6.dist-info/METADATA
request_response_logging-1.0.6.dist-info/WHEEL
request_response_logging-1.0.6.dist-info/top_level.txt
request_response_logging-1.0.6.dist-info/RECORD
