Metadata-Version: 2.4
Name: request_response_logging
Version: 1.0.6
Summary: Django logger to log request response
Author: Pravin Tiwari
Author-email: pravint198@gmail.com
Requires-Python: >=3.7
Requires-Dist: simplejson
Dynamic: author
Dynamic: author-email
Dynamic: description
Dynamic: description-content-type
Dynamic: requires-dist
Dynamic: requires-python
Dynamic: summary
